MANIFEST.in
setup.py
docs/HISTORY.txt
src/menhir/__init__.py
src/menhir.contenttype.file.egg-info/PKG-INFO
src/menhir.contenttype.file.egg-info/SOURCES.txt
src/menhir.contenttype.file.egg-info/dependency_links.txt
src/menhir.contenttype.file.egg-info/entry_points.txt
src/menhir.contenttype.file.egg-info/namespace_packages.txt
src/menhir.contenttype.file.egg-info/not-zip-safe
src/menhir.contenttype.file.egg-info/requires.txt
src/menhir.contenttype.file.egg-info/top_level.txt
src/menhir/contenttype/__init__.py
src/menhir/contenttype/file/README.txt
src/menhir/contenttype/file/__init__.py
src/menhir/contenttype/file/configure.zcml
src/menhir/contenttype/file/file.png
src/menhir/contenttype/file/file.py
src/menhir/contenttype/file/ftesting.zcml
src/menhir/contenttype/file/tests.py
src/menhir/contenttype/file/locales/fr/LC_MESSAGES/menhir.contenttype.file.mo
src/menhir/contenttype/file/locales/fr/LC_MESSAGES/menhir.contenttype.file.po