Metadata-Version: 1.0
Name: menhir.contenttype.file
Version: 0.3
Summary: File content type for Grok and Dolmen applications.
Home-page: http://pypi.python.org/pypi/menhir.contenttype.file
Author: Souheil Chelfouh
Author-email: trollfot@gmail.com
License: GPL
Keywords: Grok Dolmen File Content
Platform: UNKNOWN
Classifier: Programming Language :: Python
Classifier: Topic :: Software Development :: Libraries :: Python Modules
